pipedrive/base.py
pipedrive/pipeline.py
pipedrive/organization.py
pipedrive/__init__.py
pipedrive/resources.py
pipedrive/deal.py
pipedrive/models.py
pipedrive/user.py
pipedrive/stage.py
pipedrive/search.py
pipedrive/activity.py
pipedrive/types.py
pipedrive/fields.py
pipedrive_py-0.3.33.dist-info/RECORD
pipedrive_py-0.3.33.dist-info/top_level.txt
pipedrive_py-0.3.33.dist-info/METADATA
pipedrive_py-0.3.33.dist-info/metadata.json
pipedrive_py-0.3.33.dist-info/DESCRIPTION.rst
pipedrive_py-0.3.33.dist-info/WHEEL
