Metadata-Version: 2.0
Name: pipedrive-py
Version: 0.3.33
Summary: Python lib for the pipedrive.com api
Home-page: http://github.com/loggi/pipedrive-py/
Author: Arthur Debert
Author-email: arthur@loggi.com
License: BSD License
Platform: UNKNOWN
Classifier: Development Status :: 3 - Alpha
Classifier: Intended Audience :: Developers
Classifier: Natural Language :: English
Classifier: License :: OSI Approved :: BSD License
Classifier: Operating System :: OS Independent
Classifier: Programming Language :: Python
Classifier: Programming Language :: Python :: 2
Classifier: Programming Language :: Python :: 2.6
Classifier: Programming Language :: Python :: 2.7
Classifier: Topic :: Internet :: WWW/HTTP
Requires-Dist: schematics
Requires-Dist: requests
